Modules/coeffs_control.v
module coeffs_control (
    input clk,
    input rst,
    input clk_enable,

    input [5:0] current_count,  // current_count from counter

    input coeffs_en,  // coeffs_en from write_done_capture

    input        [ 5:0] write_address,  // o_write_address from input_register
    input signed [15:0] coeffs_in,      // o_coeffs_in from input_register
    input               write_enable,   // o_write_enable from input_register

    output signed [15:0] product_mux
);

  localparam NUMBER_OF_COEFFS = 64;

  // Coeffs registers
  // coeffs_assigned to assign coeffs_in at an address, else assign by coresponding coeffs_regs
  wire signed [15:0] coeffs_assigned[0:NUMBER_OF_COEFFS-1];
  wire signed [15:0] coeffs_temp    [0:NUMBER_OF_COEFFS-1];
  reg signed  [15:0] coeffs_regs    [0:NUMBER_OF_COEFFS-1];

  // Linking mem and address to storing new coeffs_in values
  genvar i;
  generate
    for (i = 0; i < 64; i = i + 1) begin : gen_coeffs_assigned
      // assign coeffs_assigned register with coresponding write_address to store coeffs_in value in it
      assign coeffs_assigned[i] = (write_address == i) ? coeffs_in : coeffs_regs[i];
      // if write_enable then coeffs_temp = coeffs_assigned else coeffs_regs
      assign coeffs_temp[i] = (write_enable == 1) ? coeffs_assigned[i] : coeffs_regs[i];
    end
  endgenerate

  reg [5:0] coeffs_regs_reset_index;
  reg [5:0] coeffs_regs_index;

  // Coeffs registers process
  always @(posedge clk or posedge rst) begin
    if (rst == 1) begin
      // Reset all coeffs registers
      for (
          coeffs_regs_reset_index = 0;
          coeffs_regs_reset_index < NUMBER_OF_COEFFS;
          coeffs_regs_reset_index = coeffs_regs_reset_index + 1
      ) begin
        coeffs_regs[coeffs_regs_reset_index] <= 0;
      end
    end else begin
      // coeffs_regs <= coeffs_temp if clk_enable
      if (clk_enable == 1) begin
        for (
            coeffs_regs_index = 0;
            coeffs_regs_index < NUMBER_OF_COEFFS;
            coeffs_regs_index = coeffs_regs_index + 1
        ) begin
          coeffs_regs[coeffs_regs_index] <= coeffs_temp[coeffs_regs_index];
        end
      end
    end
  end

  // Coeffs shadow register
  reg signed [15:0] coeffs_shadow[0:NUMBER_OF_COEFFS-1];

  reg [5:0] coeffs_shadow_reset_index;
  reg [5:0] coeffs_shadow_index;

  always @(posedge clk or posedge rst) begin
    if (rst == 1) begin
      // Reset all coeffs shadow registers
      for (
          coeffs_shadow_reset_index = 0;
          coeffs_shadow_reset_index < NUMBER_OF_COEFFS;
          coeffs_shadow_reset_index = coeffs_shadow_reset_index + 1
      ) begin
        coeffs_shadow[coeffs_shadow_reset_index] <= 0;
      end
    end else begin
      if (coeffs_en == 1) begin
        // coeffs_shadow <= coeffs_regs if coeffs_en
        for (
            coeffs_shadow_index = 0;
            coeffs_shadow_index < NUMBER_OF_COEFFS;
            coeffs_shadow_index = coeffs_shadow_index + 1
        ) begin
          coeffs_shadow[coeffs_shadow_index] <= coeffs_regs[coeffs_shadow_index];
        end
      end
    end
  end

  // MUXs
  // mux control

  assign product_mux = coeffs_shadow[current_count];

endmodule  //coeffs_control

Modules/write_done_capture.v
module write_done_capture (
    input clk,
    input rst,
    input clk_enable,

    input i_write_done,         // from input_register's o_write_done
    input i_control_phase_bar,  // from phase_check's control_phase_bar
    input phase_63,             // from phase_check's phase63

    output o_write_done_capture,
    output reg o_write_done_edge,
    output coeffs_en
);
  reg r_write_done_capture;
  assign o_write_done_capture = r_write_done_capture;

  reg r_phase_63;


  always @(phase_63) r_phase_63 <= phase_63;

  wire w_write_done_capture_in, w_write_done_short, w_write_done_edge_bar; // write_done_capture's wires

  assign w_write_done_capture_in = (r_write_done_capture == 1) ? i_control_phase_bar : w_write_done_short;

  assign coeffs_en = r_phase_63 & r_write_done_capture;

  assign w_write_done_edge_bar = ~(o_write_done_edge);

  assign w_write_done_short = i_write_done & w_write_done_edge_bar;

  always @(posedge clk or posedge rst) begin
    if (rst == 1) begin
      r_write_done_capture <= 0;
      o_write_done_edge    <= 0;
    end else begin
      if (clk_enable == 1) begin
        r_write_done_capture <= w_write_done_capture_in;
        o_write_done_edge    <= i_write_done;
      end
    end
  end

endmodule  //write_done_capture

Modules/input_register.v
module input_register (
    input clk,
    input rst,
    input clk_enable,

    input               i_write_enable,
    input               i_write_done,
    input        [ 5:0] i_write_address,
    input signed [15:0] i_coeffs_in,

    output reg o_write_enable,
    output reg o_write_done,
    output reg o_write_address,
    output reg o_coeffs_in
);
  always @(posedge clk or posedge rst) begin
    if (rst == 1) begin
      o_write_enable <= 0;
      o_write_done <= 0;
      o_write_address <= 0;
      o_coeffs_in <= 0;
    end else begin
      if (clk_enable == 1) begin
        o_write_enable <= i_write_enable;
        o_write_done <= i_write_done;
        o_write_address <= i_write_address;
        o_coeffs_in <= i_coeffs_in;
      end
    end
  end

endmodule  //input_register

Modules/delay_pipeline.v
module delay_pipeline (
    input clk,
    input rst,

    input               phase_63,        // from phase_check's phase_63
    // signed fixed-point 16 bit with 15 bit for fraction. Value range [-1, 1)
    input signed [15:0] i_signal_sample, // from filter's i_signal_sample

    output signed [15:0] o_delayed_sample
);

  localparam NUMBER_OF_PIPE = 64;
  integer pipe_index;

  // Define shift register
  reg signed [15:0] delay_pipeline[0:NUMBER_OF_PIPE-1];

  always @(posedge clk or posedge rst) begin
    if (rst == 1) begin
      // Reset the shift register
      for (pipe_index = 0; pipe_index < NUMBER_OF_PIPE; pipe_index = pipe_index + 1) begin
        delay_pipeline[pipe_index] <= 0;
      end
    end else begin
      if (phase_63 == 1) begin
        // Shift data through the pipeline
        for (pipe_index = NUMBER_OF_PIPE - 1; pipe_index > 0; pipe_index = pipe_index - 1) begin
          delay_pipeline[pipe_index] <= delay_pipeline[pipe_index-1];
        end
        // Load new sample into the first stage
        delay_pipeline[0] <= i_signal_sample;
      end
    end
  end

  // Output the delayed sample
  assign o_delayed_sample = delay_pipeline[NUMBER_OF_PIPE-1];

endmodule  //delay_pipeline

Modules/phase_check.v
`timescale 1 ns / 1 ns

module phase_check (
    input clk_enable,

    input [5:0] current_count,

    output phase_63,
    output phase_0,
    output control_phase_bar
);

  assign phase_63          = ((current_count == 6'b111111) && (clk_enable == 1)) ? 1 : 0;
  assign phase_0           = ((current_count == 6'b000000) && (clk_enable == 1)) ? 1 : 0;

  assign control_phase_bar = ~(phase_63);

endmodule  //phase_check

Modules/counter.v
`timescale 1 ns / 1 ns

module counter (
    input clk,
    input clk_enable,
    input rst,

    output reg [5:0] current_count
);
  always @(posedge clk or posedge rst) begin
    if (rst == 1) begin
      current_count <= 6'b111111;
    end else begin
      if (clk_enable == 1) begin
        if (current_count >= 6'b111111) begin
          current_count <= 0;
        end else begin
          current_count <= current_count + 1;
        end
      end
    end
  end

endmodule

Modules/filter.v
module filter (
    input clk,
    input clk_enable,
    input rst,

    input signed [15:0] i_signal_sample,  // filter's i_signal_sample

    input               i_write_enable,
    input               i_write_done,
    input        [ 5:0] i_write_address,
    input signed [15:0] i_coeffs_in


);
  // region counter
  wire [5:0] current_count;  // from counter's current_count

  counter counter_inst (
      .clk(clk),
      .clk_enable(clk_enable),
      .rst(rst),

      .current_count(current_count)
  );
  // endregion counter

  // region phase_check
  wire phase_63, phase_0, control_phase_bar; // from phase_check's phase_63, phase_0, control_phase_bar

  phase_check phase_check_inst (
      .clk_enable(clk_enable),

      .current_count(current_count),

      .phase_63(phase_63),
      .phase_0(phase_0),
      .control_phase_bar(control_phase_bar)
  );
  // endregion phase_check

  // region delay_pipeline
  delay_pipeline delay_pipeline_inst (
      .clk(clk),
      .rst(rst),

      .phase_63(phase_63),
      .i_signal_sample(i_signal_sample)
  );
  // endregion delay_pipeline

  // region input_register
  wire write_enable, write_done, write_address, coeffs_in; // from input_register's o_write_enable, o_write_done, o_write_address, o_coeffs_in

  input_register input_register_inst (
      .clk(clk),
      .rst(rst),
      .clk_enable(clk_enable),

      .i_write_enable(i_write_enable),
      .i_write_done(i_write_done),
      .i_write_address(i_write_address),
      .i_coeffs_in(i_coeffs_in),

      .o_write_enable(write_enable),
      .o_write_done(write_done),
      .o_write_address(write_address),
      .o_coeffs_in(coeffs_in)
  );

  // endregion input_register

  // region write_done_capture
  wire o_write_done_capture, o_write_done_edge, coeffs_en;  //write_done_capture's o_write_done_capture, o_write_done_edge, coeffs_en
  write_done_capture write_done_capture_inst (
      .clk(clk),
      .rst(rst),
      .clk_enable(clk_enable),

      .i_write_done(write_done),
      .i_control_phase_bar(control_phase_bar),
      .phase_63(phase_63),

      .o_write_done_capture(o_write_done_capture),
      .o_write_done_edge(o_write_done_edge),
      .coeffs_en(coeffs_en)
  );

  // endregion write_done_capture

  // region coeffs_control
  coeffs_control coeffs_control_inst (
      .clk(clk),
      .rst(rst),
      .clk_enable(clk_enable),

      .current_count(current_count),  // current_count from counter

      .coeffs_en(coeffs_en),  // coeffs_en from write_done_capture

      .write_address(write_address),  // o_write_address from input_register
      .coeffs_in    (coeffs_in),      // o_coeffs_in from input_register
      .write_enable (write_enable),   // o_write_enable from input_register
  );
  // endregion coeffs_control

endmodule  //filter

Modules/filter_tb.v
// python compile.py phase_check phase_check.v phase_check_tb.v counter.v
`timescale 1ns / 1ps

module filter_tb;

  reg                clk = 0;
  reg                rst = 0;
  reg                clk_enable = 1;

  reg signed [15:0] i_signal_sample;  // filter's i_signal_sample

  wire               i_write_enable;
  wire               i_write_done;
  wire        [ 5:0] i_write_address;
  wire signed [15:0] i_coeffs_in;

  filter uut (
      .clk(clk),
      .rst(rst),
      .clk_enable(clk_enable),

      .i_signal_sample(i_signal_sample),

      .i_write_enable(i_write_enable),
      .i_write_done(i_write_done),
      .i_write_address(i_write_address),
      .i_coeffs_in(i_coeffs_in)
  );

  parameter CLK_PERIOD = 10;  // 100MHz clock = 10ns period
  always #((CLK_PERIOD) / 2) clk = ~clk;

  initial begin
    $dumpfile("./Simulate/filter.vcd");
    $dumpvars;
    rst = 1;
    i_signal_sample = 0;
    #(CLK_PERIOD * 10);
    rst = 0;
    #(CLK_PERIOD * 20000);
    $finish;
  end

  always #(CLK_PERIOD * 1000) begin
    i_signal_sample = $signed($urandom_range(1, 200));
  end

endmodule  //counter_tb

Modules/Simulate/filter.vcd
$date
	Wed Apr  3 22:16:43 2024
$end
$version
	Icarus Verilog
$end
$timescale
	1ps
$end
$scope module filter_tb $end
$var wire 16 ! i_coeffs_in [15:0] $end
$var wire 6 " i_write_address [5:0] $end
$var wire 1 # i_write_done $end
$var wire 1 $ i_write_enable $end
$var parameter 32 % CLK_PERIOD $end
$var reg 1 & clk $end
$var reg 1 ' clk_enable $end
$var reg 16 ( i_signal_sample [15:0] $end
$var reg 1 ) rst $end
$scope module uut $end
$var wire 1 & clk $end
$var wire 1 ' clk_enable $end
$var wire 16 * i_coeffs_in [15:0] $end
$var wire 16 + i_signal_sample [15:0] $end
$var wire 6 , i_write_address [5:0] $end
$var wire 1 # i_write_done $end
$var wire 1 $ i_write_enable $end
$var wire 1 ) rst $end
$var wire 1 - write_enable $end
$var wire 1 . write_done $end
$var wire 1 / write_address $end
$var wire 1 0 phase_63 $end
$var wire 1 1 phase_0 $end
$var wire 1 2 o_write_done_edge $end
$var wire 1 3 o_write_done_capture $end
$var wire 6 4 current_count [5:0] $end
$var wire 1 5 control_phase_bar $end
$var wire 1 6 coeffs_in $end
$var wire 1 7 coeffs_en $end
$scope module counter_inst $end
$var wire 1 & clk $end
$var wire 1 ' clk_enable $end
$var wire 1 ) rst $end
$var reg 6 8 current_count [5:0] $end
$upscope $end
$scope module delay_pipeline_inst $end
$var wire 1 & clk $end
$var wire 16 9 i_signal_sample [15:0] $end
$var wire 16 : o_delayed_sample [15:0] $end
$var wire 1 ) rst $end
$var wire 1 0 phase_63 $end
$var parameter 32 ; NUMBER_OF_PIPE $end
$var integer 32 < pipe_index [31:0] $end
$upscope $end
$scope module input_register_inst $end
$var wire 1 & clk $end
$var wire 1 ' clk_enable $end
$var wire 16 = i_coeffs_in [15:0] $end
$var wire 6 > i_write_address [5:0] $end
$var wire 1 # i_write_done $end
$var wire 1 $ i_write_enable $end
$var wire 1 ) rst $end
$var reg 1 6 o_coeffs_in $end
$var reg 1 / o_write_address $end
$var reg 1 . o_write_done $end
$var reg 1 - o_write_enable $end
$upscope $end
$scope module phase_check_inst $end
$var wire 1 ' clk_enable $end
$var wire 1 5 control_phase_bar $end
$var wire 6 ? current_count [5:0] $end
$var wire 1 0 phase_63 $end
$var wire 1 1 phase_0 $end
$upscope $end
$scope module write_done_capture_inst $end
$var wire 1 & clk $end
$var wire 1 ' clk_enable $end
$var wire 1 7 coeffs_en $end
$var wire 1 5 i_control_phase_bar $end
$var wire 1 . i_write_done $end
$var wire 1 3 o_write_done_capture $end
$var wire 1 0 phase_63 $end
$var wire 1 ) rst $end
$var wire 1 @ w_write_done_edge_bar $end
$var wire 1 A w_write_done_short $end
$var wire 1 B w_write_done_capture_in $end
$var reg 1 2 o_write_done_edge $end
$var reg 1 C r_phase_63 $end
$var reg 1 D r_write_done_capture $end
$upscope $end
$upscope $end
$upscope $end
$enddefinitions $end
$comment Show the parameter values. $end
$dumpall
b1000000 ;
b1010 %
$end
#0
$dumpvars
0D
1C
0B
0A
1@
b111111 ?
bz >
bz =
b1000000 <
b0 :
b0 9
b111111 8
07
06
05
b111111 4
03
02
01
10
0/
0.
0-
bz ,
b0 +
bz *
1)
b0 (
1'
0&
z$
z#
bz "
bz !
$end
#5000
b1000000 <
1&
#10000
0&
#15000
b1000000 <
1&
#20000
0&
#25000
b1000000 <
1&
#30000
0&
#35000
b1000000 <
1&
#40000
0&
#45000
b1000000 <
1&
#50000
0&
#55000
b1000000 <
1&
#60000
0&
#65000
b1000000 <
1&
#70000
0&
#75000
b1000000 <
1&
#80000
0&
#85000
b1000000 <
1&
#90000
0&
#95000
b1000000 <
1&
#100000
0&
0)
#105000
0C
15
00
11
xB
xA
z6
z/
z.
z-
b0 4
b0 8
b0 ?
b0 <
1&
#110000
0&
#115000
01
x@
b1 4
b1 8
b1 ?
z2
x3
xD
1&
#120000
0&
#125000
b10 4
b10 8
b10 ?
1&
#130000
0&
#135000
b11 4
b11 8
b11 ?
1&
#140000
0&
#145000
b100 4
b100 8
b100 ?
1&
#150000
0&
#155000
b101 4
b101 8
b101 ?
1&
#160000
0&
#165000
b110 4
b110 8
b110 ?
1&
#170000
0&
#175000
b111 4
b111 8
b111 ?
1&
#180000
0&
#185000
b1000 4
b1000 8
b1000 ?
1&
#190000
0&
#195000
b1001 4
b1001 8
b1001 ?
1&
#200000
0&
#205000
b1010 4
b1010 8
b1010 ?
1&
#210000
0&
#215000
b1011 4
b1011 8
b1011 ?
1&
#220000
0&
#225000
b1100 4
b1100 8
b1100 ?
1&
#230000
0&
#235000
b1101 4
b1101 8
b1101 ?
1&
#240000
0&
#245000
b1110 4
b1110 8
b1110 ?
1&
#250000
0&
#255000
b1111 4
b1111 8
b1111 ?
1&
#260000
0&
#265000
b10000 4
b10000 8
b10000 ?
1&
#270000
0&
#275000
b10001 4
b10001 8
b10001 ?
1&
#280000
0&
#285000
b10010 4
b10010 8
b10010 ?
1&
#290000
0&
#295000
b10011 4
b10011 8
b10011 ?
1&
#300000
0&
#305000
b10100 4
b10100 8
b10100 ?
1&
#310000
0&
#315000
b10101 4
b10101 8
b10101 ?
1&
#320000
0&
#325000
b10110 4
b10110 8
b10110 ?
1&
#330000
0&
#335000
b10111 4
b10111 8
b10111 ?
1&
#340000
0&
#345000
b11000 4
b11000 8
b11000 ?
1&
#350000
0&
#355000
b11001 4
b11001 8
b11001 ?
1&
#360000
0&
#365000
b11010 4
b11010 8
b11010 ?
1&
#370000
0&
#375000
b11011 4
b11011 8
b11011 ?
1&
#380000
0&
#385000
b11100 4
b11100 8
b11100 ?
1&
#390000
0&
#395000
b11101 4
b11101 8
b11101 ?
1&
#400000
0&
#405000
b11110 4
b11110 8
b11110 ?
1&
#410000
0&
#415000
b11111 4
b11111 8
b11111 ?
1&
#420000
0&
#425000
b100000 4
b100000 8
b100000 ?
1&
#430000
0&
#435000
b100001 4
b100001 8
b100001 ?
1&
#440000
0&
#445000
b100010 4
b100010 8
b100010 ?
1&
#450000
0&
#455000
b100011 4
b100011 8
b100011 ?
1&
#460000
0&
#465000
b100100 4
b100100 8
b100100 ?
1&
#470000
0&
#475000
b100101 4
b100101 8
b100101 ?
1&
#480000
0&
#485000
b100110 4
b100110 8
b100110 ?
1&
#490000
0&
#495000
b100111 4
b100111 8
b100111 ?
1&
#500000
0&
#505000
b101000 4
b101000 8
b101000 ?
1&
#510000
0&
#515000
b101001 4
b101001 8
b101001 ?
1&
#520000
0&
#525000
b101010 4
b101010 8
b101010 ?
1&
#530000
0&
#535000
b101011 4
b101011 8
b101011 ?
1&
#540000
0&
#545000
b101100 4
b101100 8
b101100 ?
1&
#550000
0&
#555000
b101101 4
b101101 8
b101101 ?
1&
#560000
0&
#565000
b101110 4
b101110 8
b101110 ?
1&
#570000
0&
#575000
b101111 4
b101111 8
b101111 ?
1&
#580000
0&
#585000
b110000 4
b110000 8
b110000 ?
1&
#590000
0&
#595000
b110001 4
b110001 8
b110001 ?
1&
#600000
0&
#605000
b110010 4
b110010 8
b110010 ?
1&
#610000
0&
#615000
b110011 4
b110011 8
b110011 ?
1&
#620000
0&
#625000
b110100 4
b110100 8
b110100 ?
1&
#630000
0&
#635000
b110101 4
b110101 8
b110101 ?
1&
#640000
0&
#645000
b110110 4
b110110 8
b110110 ?
1&
#650000
0&
#655000
b110111 4
b110111 8
b110111 ?
1&
#660000
0&
#665000
b111000 4
b111000 8
b111000 ?
1&
#670000
0&
#675000
b111001 4
b111001 8
b111001 ?
1&
#680000
0&
#685000
b111010 4
b111010 8
b111010 ?
1&
#690000
0&
#695000
b111011 4
b111011 8
b111011 ?
1&
#700000
0&
#705000
b111100 4
b111100 8
b111100 ?
1&
#710000
0&
#715000
b111101 4
b111101 8
b111101 ?
1&
#720000
0&
#725000
b111110 4
b111110 8
b111110 ?
1&
#730000
0&
#735000
x7
1C
05
10
b111111 4
b111111 8
b111111 ?
1&
#740000
0&
#745000
07
0C
15
00
11
b0 4
b0 8
b0 ?
b0 <
1&
#750000
0&
#755000
01
b1 4
b1 8
b1 ?
1&
#760000
0&
#765000
b10 4
b10 8
b10 ?
1&
#770000
0&
#775000
b11 4
b11 8
b11 ?
1&
#780000
0&
#785000
b100 4
b100 8
b100 ?
1&
#790000
0&
#795000
b101 4
b101 8
b101 ?
1&
#800000
0&
#805000
b110 4
b110 8
b110 ?
1&
#810000
0&
#815000
b111 4
b111 8
b111 ?
1&
#820000
0&
#825000
b1000 4
b1000 8
b1000 ?
1&
#830000
0&
#835000
b1001 4
b1001 8
b1001 ?
1&
#840000
0&
#845000
b1010 4
b1010 8
b1010 ?
1&
#850000
0&
#855000
b1011 4
b1011 8
b1011 ?
1&
#860000
0&
#865000
b1100 4
b1100 8
b1100 ?
1&
#870000
0&
#875000
b1101 4
b1101 8
b1101 ?
1&
#880000
0&
#885000
b1110 4
b1110 8
b1110 ?
1&
#890000
0&
#895000
b1111 4
b1111 8
b1111 ?
1&
#900000
0&
#905000
b10000 4
b10000 8
b10000 ?
1&
#910000
0&
#915000
b10001 4
b10001 8
b10001 ?
1&
#920000
0&
#925000
b10010 4
b10010 8
b10010 ?
1&
#930000
0&
#935000
b10011 4
b10011 8
b10011 ?
1&
#940000
0&
#945000
b10100 4
b10100 8
b10100 ?
1&
#950000
0&
#955000
b10101 4
b10101 8
b10101 ?
1&
#960000
0&
#965000
b10110 4
b10110 8
b10110 ?
1&
#970000
0&
#975000
b10111 4
b10111 8
b10111 ?
1&
#980000
0&
#985000
b11000 4
b11000 8
b11000 ?
1&
#990000
0&
#995000
b11001 4
b11001 8
b11001 ?
1&
#1000000
0&
#1005000
b11010 4
b11010 8
b11010 ?
1&
#1010000
0&
#1015000
b11011 4
b11011 8
b11011 ?
1&
#1020000
0&
#1025000
b11100 4
b11100 8
b11100 ?
1&
#1030000
0&
#1035000
b11101 4
b11101 8
b11101 ?
1&
#1040000
0&
#1045000
b11110 4
b11110 8
b11110 ?
1&
#1050000
0&
#1055000
b11111 4
b11111 8
b11111 ?
1&
#1060000
0&
#1065000
b100000 4
b100000 8
b100000 ?
1&
#1070000
0&
#1075000
b100001 4
b100001 8
b100001 ?
1&
#1080000
0&
#1085000
b100010 4
b100010 8
b100010 ?
1&
#1090000
0&
#1095000
b100011 4
b100011 8
b100011 ?
1&
#1100000
0&
#1105000
b100100 4
b100100 8
b100100 ?
1&
#1110000
0&
#1115000
b100101 4
b100101 8
b100101 ?
1&
#1120000
0&
#1125000
b100110 4
b100110 8
b100110 ?
1&
#1130000
0&
#1135000
b100111 4
b100111 8
b100111 ?
1&
#1140000
0&
#1145000
b101000 4
b101000 8
b101000 ?
1&
#1150000
0&
#1155000
b101001 4
b101001 8
b101001 ?
1&
#1160000
0&
#1165000
b101010 4
b101010 8
b101010 ?
1&
#1170000
0&
#1175000
b101011 4
b101011 8
b101011 ?
1&
#1180000
0&
#1185000
b101100 4
b101100 8
b101100 ?
1&
#1190000
0&
#1195000
b101101 4
b101101 8
b101101 ?
1&
#1200000
0&
#1205000
b101110 4
b101110 8
b101110 ?
1&
#1210000
0&
#1215000
b101111 4
b101111 8
b101111 ?
1&
#1220000
0&
#1225000
b110000 4
b110000 8
b110000 ?
1&
#1230000
0&
#1235000
b110001 4
b110001 8
b110001 ?
1&
#1240000
0&
#1245000
b110010 4
b110010 8
b110010 ?
1&
#1250000
0&
#1255000
b110011 4
b110011 8
b110011 ?
1&
#1260000
0&
#1265000
b110100 4
b110100 8
b110100 ?
1&
#1270000
0&
#1275000
b110101 4
b110101 8
b110101 ?
1&
#1280000
0&
#1285000
b110110 4
b110110 8
b110110 ?
1&
#1290000
0&
#1295000
b110111 4
b110111 8
b110111 ?
1&
#1300000
0&
#1305000
b111000 4
b111000 8
b111000 ?
1&
#1310000
0&
#1315000
b111001 4
b111001 8
b111001 ?
1&
#1320000
0&
#1325000
b111010 4
b111010 8
b111010 ?
1&
#1330000
0&
#1335000
b111011 4
b111011 8
b111011 ?
1&
#1340000
0&
#1345000
b111100 4
b111100 8
b111100 ?
1&
#1350000
0&
#1355000
b111101 4
b111101 8
b111101 ?
1&
#1360000
0&
#1365000
b111110 4
b111110 8
b111110 ?
1&
#1370000
0&
#1375000
x7
1C
05
10
b111111 4
b111111 8
b111111 ?
1&
#1380000
0&
#1385000
07
0C
15
00
11
b0 4
b0 8
b0 ?
b0 <
1&
#1390000
0&
#1395000
01
b1 4
b1 8
b1 ?
1&
#1400000
0&
#1405000
b10 4
b10 8
b10 ?
1&
#1410000
0&
#1415000
b11 4
b11 8
b11 ?
1&
#1420000
0&
#1425000
b100 4
b100 8
b100 ?
1&
#1430000
0&
#1435000
b101 4
b101 8
b101 ?
1&
#1440000
0&
#1445000
b110 4
b110 8
b110 ?
1&
#1450000
0&
#1455000
b111 4
b111 8
b111 ?
1&
#1460000
0&
#1465000
b1000 4
b1000 8
b1000 ?
1&
#1470000
0&
#1475000
b1001 4
b1001 8
b1001 ?
1&
#1480000
0&
#1485000
b1010 4
b1010 8
b1010 ?
1&
#1490000
0&
#1495000
b1011 4
b1011 8
b1011 ?
1&
#1500000
0&
#1505000
b1100 4
b1100 8
b1100 ?
1&
#1510000
0&
#1515000
b1101 4
b1101 8
b1101 ?
1&
#1520000
0&
#1525000
b1110 4
b1110 8
b1110 ?
1&
#1530000
0&
#1535000
b1111 4
b1111 8
b1111 ?
1&
#1540000
0&
#1545000
b10000 4
b10000 8
b10000 ?
1&
#1550000
0&
#1555000
b10001 4
b10001 8
b10001 ?
1&
#1560000
0&
#1565000
b10010 4
b10010 8
b10010 ?
1&
#1570000
0&
#1575000
b10011 4
b10011 8
b10011 ?
1&
#1580000
0&
#1585000
b10100 4
b10100 8
b10100 ?
1&
#1590000
0&
#1595000
b10101 4
b10101 8
b10101 ?
1&
#1600000
0&
#1605000
b10110 4
b10110 8
b10110 ?
1&
#1610000
0&
#1615000
b10111 4
b10111 8
b10111 ?
1&
#1620000
0&
#1625000
b11000 4
b11000 8
b11000 ?
1&
#1630000
0&
#1635000
b11001 4
b11001 8
b11001 ?
1&
#1640000
0&
#1645000
b11010 4
b11010 8
b11010 ?
1&
#1650000
0&
#1655000
b11011 4
b11011 8
b11011 ?
1&
#1660000
0&
#1665000
b11100 4
b11100 8
b11100 ?
1&
#1670000
0&
#1675000
b11101 4
b11101 8
b11101 ?
1&
#1680000
0&
#1685000
b11110 4
b11110 8
b11110 ?
1&
#1690000
0&
#1695000
b11111 4
b11111 8
b11111 ?
1&
#1700000
0&
#1705000
b100000 4
b100000 8
b100000 ?
1&
#1710000
0&
#1715000
b100001 4
b100001 8
b100001 ?
1&
#1720000
0&
#1725000
b100010 4
b100010 8
b100010 ?
1&
#1730000
0&
#1735000
b100011 4
b100011 8
b100011 ?
1&
#1740000
0&
#1745000
b100100 4
b100100 8
b100100 ?
1&
#1750000
0&
#1755000
b100101 4
b100101 8
b100101 ?
1&
#1760000
0&
#1765000
b100110 4
b100110 8
b100110 ?
1&
#1770000
0&
#1775000
b100111 4
b100111 8
b100111 ?
1&
#1780000
0&
#1785000
b101000 4
b101000 8
b101000 ?
1&
#1790000
0&
#1795000
b101001 4
b101001 8
b101001 ?
1&
#1800000
0&
#1805000
b101010 4
b101010 8
b101010 ?
1&
#1810000
0&
#1815000
b101011 4
b101011 8
b101011 ?
1&
#1820000
0&
#1825000
b101100 4
b101100 8
b101100 ?
1&
#1830000
0&
#1835000
b101101 4
b101101 8
b101101 ?
1&
#1840000
0&
#1845000
b101110 4
b101110 8
b101110 ?
1&
#1850000
0&
#1855000
b101111 4
b101111 8
b101111 ?
1&
#1860000
0&
#1865000
b110000 4
b110000 8
b110000 ?
1&
#1870000
0&
#1875000
b110001 4
b110001 8
b110001 ?
1&
#1880000
0&
#1885000
b110010 4
b110010 8
b110010 ?
1&
#1890000
0&
#1895000
b110011 4
b110011 8
b110011 ?
1&
#1900000
0&
#1905000
b110100 4
b110100 8
b110100 ?
1&
#1910000
0&
#1915000
b110101 4
b110101 8
b110101 ?
1&
#1920000
0&
#1925000
b110110 4
b110110 8
b110110 ?
1&
#1930000
0&
#1935000
b110111 4
b110111 8
b110111 ?
1&
#1940000
0&
#1945000
b111000 4
b111000 8
b111000 ?
1&
#1950000
0&
#1955000
b111001 4
b111001 8
b111001 ?
1&
#1960000
0&
#1965000
b111010 4
b111010 8
b111010 ?
1&
#1970000
0&
#1975000
b111011 4
b111011 8
b111011 ?
1&
#1980000
0&
#1985000
b111100 4
b111100 8
b111100 ?
1&
#1990000
0&
#1995000
b111101 4
b111101 8
b111101 ?
1&
#2000000
0&
#2005000
b111110 4
b111110 8
b111110 ?
1&
#2010000
0&
#2015000
x7
1C
05
10
b111111 4
b111111 8
b111111 ?
1&
#2020000
0&
#2025000
07
0C
15
00
11
b0 4
b0 8
b0 ?
b0 <
1&
#2030000
0&
#2035000
01
b1 4
b1 8
b1 ?
1&
#2040000
0&
#2045000
b10 4
b10 8
b10 ?
1&
#2050000
0&
#2055000
b11 4
b11 8
b11 ?
1&
#2060000
0&
#2065000
b100 4
b100 8
b100 ?
1&
#2070000
0&
#2075000
b101 4
b101 8
b101 ?
1&
#2080000
0&
#2085000
b110 4
b110 8
b110 ?
1&
#2090000
0&
#2095000
b111 4
b111 8
b111 ?
1&
#2100000
0&
#2105000
b1000 4
b1000 8
b1000 ?
1&
#2110000
0&
#2115000
b1001 4
b1001 8
b1001 ?
1&
#2120000
0&
#2125000
b1010 4
b1010 8
b1010 ?
1&
#2130000
0&
#2135000
b1011 4
b1011 8
b1011 ?
1&
#2140000
0&
#2145000
b1100 4
b1100 8
b1100 ?
1&
#2150000
0&
#2155000
b1101 4
b1101 8
b1101 ?
1&
#2160000
0&
#2165000
b1110 4
b1110 8
b1110 ?
1&
#2170000
0&
#2175000
b1111 4
b1111 8
b1111 ?
1&
#2180000
0&
#2185000
b10000 4
b10000 8
b10000 ?
1&
#2190000
0&
#2195000
b10001 4
b10001 8
b10001 ?
1&
#2200000
0&
#2205000
b10010 4
b10010 8
b10010 ?
1&
#2210000
0&
#2215000
b10011 4
b10011 8
b10011 ?
1&
#2220000
0&
#2225000
b10100 4
b10100 8
b10100 ?
1&
#2230000
0&
#2235000
b10101 4
b10101 8
b10101 ?
1&
#2240000
0&
#2245000
b10110 4
b10110 8
b10110 ?
1&
#2250000
0&
#2255000
b10111 4
b10111 8
b10111 ?
1&
#2260000
0&
#2265000
b11000 4
b11000 8
b11000 ?
1&
#2270000
0&
#2275000
b11001 4
b11001 8
b11001 ?
1&
#2280000
0&
#2285000
b11010 4
b11010 8
b11010 ?
1&
#2290000
0&
#2295000
b11011 4
b11011 8
b11011 ?
1&
#2300000
0&
#2305000
b11100 4
b11100 8
b11100 ?
1&
#2310000
0&
#2315000
b11101 4
b11101 8
b11101 ?
1&
#2320000
0&
#2325000
b11110 4
b11110 8
b11110 ?
1&
#2330000
0&
#2335000
b11111 4
b11111 8
b11111 ?
1&
#2340000
0&
#2345000
b100000 4
b100000 8
b100000 ?
1&
#2350000
0&
#2355000
b100001 4
b100001 8
b100001 ?
1&
#2360000
0&
#2365000
b100010 4
b100010 8
b100010 ?
1&
#2370000
0&
#2375000
b100011 4
b100011 8
b100011 ?
1&
#2380000
0&
#2385000
b100100 4
b100100 8
b100100 ?
1&
#2390000
0&
#2395000
b100101 4
b100101 8
b100101 ?
1&
#2400000
0&
#2405000
b100110 4
b100110 8
b100110 ?
1&
#2410000
0&
#2415000
b100111 4
b100111 8
b100111 ?
1&
#2420000
0&
#2425000
b101000 4
b101000 8
b101000 ?
1&
#2430000
0&
#2435000
b101001 4
b101001 8
b101001 ?
1&
#2440000
0&
#2445000
b101010 4
b101010 8
b101010 ?
1&
#2450000
0&
