Modules/z_block.v
module z_block (
    input         clk,
    input         rst,
    input  [15:0] data_in,
    output reg [15:0] data_out
);

  always @(posedge clk or posedge rst) begin
    if (rst) data_out <= 0;
    else begin
      data_out <= data_in;
    end
  end

endmodule  //z_block

Modules/z_block_tb.v
`timescale 1ns / 1ps

module z_block_tb ();
  reg clk = 0, rst = 0;
  reg  [15:0] data_in = 0;
  wire [15:0] data_out;

  parameter CLK_PERIOD = 10;
  always #(CLK_PERIOD / 2) clk = ~clk;

  z_block dut (
      .clk(clk),
      .rst(rst),
      .data_in(data_in),
      .data_out(data_out)
  );

  initial begin
    $dumpfile("./Simulate/timer1hz.vcd");
    $dumpvars;
    rst = 1;
    #(CLK_PERIOD * 3);
    rst = 0;
    data_in = 69;
    #CLK_PERIOD;
    data_in = 88;
    #CLK_PERIOD;
    data_in = 99;
    #(CLK_PERIOD * 3);
    rst = 1;
    #(CLK_PERIOD * 3);
    rst = 0;
    data_in <= 123;
    #(CLK_PERIOD * 10);
    $finish;
  end

endmodule  //z_block_tb

Modules/Simulate/timer1hz.vcd
$date
	Sat Mar 30 15:28:23 2024
$end
$version
	Icarus Verilog
$end
$timescale
	1ps
$end
$scope module z_block_tb $end
$var wire 16 ! data_out [15:0] $end
$var parameter 32 " CLK_PERIOD $end
$var reg 1 # clk $end
$var reg 16 $ data_in [15:0] $end
$var reg 1 % rst $end
$scope module dut $end
$var wire 1 # clk $end
$var wire 16 & data_in [15:0] $end
$var wire 1 % rst $end
$var reg 16 ' data_out [15:0] $end
$upscope $end
$upscope $end
$enddefinitions $end
$comment Show the parameter values. $end
$dumpall
b1010 "
$end
#0
$dumpvars
b0 '
b0 &
1%
b0 $
0#
b0 !
$end
#5000
1#
#10000
0#
#15000
1#
#20000
0#
#25000
1#
#30000
0#
b1000101 $
b1000101 &
0%
#35000
b1000101 !
b1000101 '
1#
#40000
0#
b1011000 $
b1011000 &
#45000
b1011000 !
b1011000 '
1#
#50000
0#
b1100011 $
b1100011 &
#55000
b1100011 !
b1100011 '
1#
#60000
0#
#65000
1#
#70000
0#
#75000
1#
#80000
b0 !
b0 '
0#
1%
#85000
1#
#90000
0#
#95000
1#
#100000
0#
#105000
1#
#110000
b1111011 $
b1111011 &
0#
0%
#115000
b1111011 !
b1111011 '
1#
